xkeys_attr/__init__.py
xkeys_crt/__init__.py
xkeys_crt/cert.py
xkeys_crt/make.py
xkeys_crt/meta.py
xkeys_ssh/__init__.py
xkeys_ssh/pair.py
xkeys_ssh/ring.py
xkeys-0.6.2.dist-info/LICENSE
xkeys-0.6.2.dist-info/METADATA
xkeys-0.6.2.dist-info/WHEEL
xkeys-0.6.2.dist-info/top_level.txt
xkeys-0.6.2.dist-info/zip-safe
xkeys-0.6.2.dist-info/RECORD
