Metadata-Version: 2.1
Name: xkeys
Version: 0.6.2
Summary: Key and Certificate Management
Home-page: https://github.com/bondbox/xkeys/
Author: Mingzhe Zou
Author-email: zoumingzhe@outlook.com
License: GPLv2
Project-URL: Source Code, https://github.com/bondbox/xkeys/
Project-URL: Bug Tracker, https://github.com/bondbox/xkeys/issues
Project-URL: Documentation, https://github.com/bondbox/xkeys/
Keywords: command-line,argparse,argcomplete
Platform: any
Classifier: Programming Language :: Python
Classifier: Programming Language :: Python :: 3
Requires-Python: >=3.8
License-File: LICENSE
Requires-Dist: xkits-logger >=0.2
Requires-Dist: xkits-file >=0.7
Requires-Dist: xkits-lib >=0.4
Requires-Dist: cryptography
Requires-Dist: toml
